ffpuppet/__init__.py
ffpuppet/__main__.py
ffpuppet/asan_symbolize.py
ffpuppet/bootstrapper.py
ffpuppet/checks.py
ffpuppet/cmds.gdb
ffpuppet/core.py
ffpuppet/display.py
ffpuppet/exceptions.py
ffpuppet/helpers.py
ffpuppet/job_object.py
ffpuppet/lsof.py
ffpuppet/main.py
ffpuppet/minidump_parser.py
ffpuppet/process_tree.py
ffpuppet/profile.py
ffpuppet/puppet_logger.py
ffpuppet/py.typed
ffpuppet/sanitizer_util.py
ffpuppet/test_bootstrapper.py
ffpuppet/test_checks.py
ffpuppet/test_display.py
ffpuppet/test_ffpuppet.py
ffpuppet/test_helpers.py
ffpuppet/test_job_object.py
ffpuppet/test_main.py
ffpuppet/test_minidump_parser.py
ffpuppet/test_process_tree.py
ffpuppet/test_profile.py
ffpuppet/test_puppet_logger.py
ffpuppet/test_sanitizer_util.py
ffpuppet/resources/testff.py
ffpuppet/resources/tree.py
ffpuppet-0.18.7.dist-info/licenses/LICENSE
ffpuppet-0.18.7.dist-info/METADATA
ffpuppet-0.18.7.dist-info/WHEEL
ffpuppet-0.18.7.dist-info/entry_points.txt
ffpuppet-0.18.7.dist-info/top_level.txt
ffpuppet-0.18.7.dist-info/RECORD
