Metadata-Version: 2.4
Name: ffpuppet
Version: 0.18.7
Summary: A Python module that aids in the automation of Firefox at the process level
Home-page: https://github.com/MozillaSecurity/ffpuppet
Author: Tyson Smith
Author-email: twsmith@mozilla.com
Maintainer: Mozilla Fuzzing Team
Maintainer-email: fuzzing@mozilla.com
License: MPL 2.0
Keywords: automation firefox fuzz fuzzing security test testing
Classifier: Intended Audience :: Developers
Classifier: License :: OSI Approved :: Mozilla Public License 2.0 (MPL 2.0)
Classifier: Programming Language :: Python :: 3
Classifier: Topic :: Software Development :: Testing
Requires-Python: >=3.9
License-File: LICENSE
Requires-Dist: psutil>=5.9.0
Requires-Dist: xvfbwrapper>=0.2.10; sys_platform == "linux"
Provides-Extra: dev
Requires-Dist: pre-commit; extra == "dev"
Requires-Dist: tox; extra == "dev"
Dynamic: license-file
